poetry_common_demo/__init__.py
poetry_common_demo/helloworld.py
poetry_common_demo-0.1.2.dist-info/METADATA
poetry_common_demo-0.1.2.dist-info/WHEEL
poetry_common_demo-0.1.2.dist-info/RECORD
