Metadata-Version: 2.3
Name: poetry-common-demo
Version: 0.1.2
Summary: testing poetry
Author: Jeremy Freiburger [I]
Author-email: jfreiburger@tesla.com
Requires-Python: >=3.13
Classifier: Programming Language :: Python :: 3
Classifier: Programming Language :: Python :: 3.13
